team_allocator/__init__.py
team_allocator/team_generator.py
tests/__init__.py
tests/test_team_generator.py
team_allocator-0.1.0.dist-info/METADATA
team_allocator-0.1.0.dist-info/WHEEL
team_allocator-0.1.0.dist-info/top_level.txt
team_allocator-0.1.0.dist-info/RECORD
