Metadata-Version: 2.1
Name: team_allocator
Version: 0.1.0
Summary: A flexible team allocation library
Home-page: https://github.com/whyvineet/team_allocator
Author: Vineet Kumar
Author-email: whyvineet@outlook.com
Classifier: Programming Language :: Python :: 3
Classifier: License :: OSI Approved :: MIT License
Classifier: Operating System :: OS Independent
Requires-Python: >=3.7
Provides-Extra: dev
Requires-Dist: pytest ; extra == 'dev'
Requires-Dist: twine ; extra == 'dev'
Requires-Dist: wheel ; extra == 'dev'
